henryhzy/__init__.py
henryhzy-0.0.0.dist-info/LICENSE
henryhzy-0.0.0.dist-info/METADATA
henryhzy-0.0.0.dist-info/WHEEL
henryhzy-0.0.0.dist-info/entry_points.txt
henryhzy-0.0.0.dist-info/top_level.txt
henryhzy-0.0.0.dist-info/RECORD
