Metadata-Version: 2.1
Name: henryhzy
Version: 0.0.0
Summary: Just for testing.
Home-page: https://henryhzy.github.io/
Author: henryhzy
Author-email: henryhuzy@gmail.com
License: MIT
Platform: UNKNOWN
